{
  "work_experience":[{
        "start_from":"Sept 2021",
        "end_to":"Present",
        "job_title":"Professional 1 Application Delivery",
        "comapany_name":"DXC Technology",
        "location":"Hyderabad, Telangana, India",
        "logo":"https://supdpk.github.io/api/assets/dxc.png"
    },
    {
        "start_from":"Sept 2019",
        "end_to":"Aug 2021",
        "job_title":"Software Developer",
        "comapany_name":"DishTV India Limited",
        "location":"Noida, Uttar Pradesh, India",
        "logo":"https://supdpk.github.io/api/assets/dish.png"
    },
    {
        "start_from":"Nov 2018",
        "end_to":"Sept 2019",
        "job_title":"Junior Software Developer",
        "comapany_name":"Parangat Technologies",
        "location":"Noida, Uttar Pradesh, India",
        "logo":"https://supdpk.github.io/api/assets/parangat.png"
    }]
}
